setup.py
racegym2d/__init__.py
racegym2d/bound_checker.py
racegym2d/env_basic.py
racegym2d/env_rays.py
racegym2d/env_rays_regrew.py
racegym2d/env_visual.py
racegym2d/env_visual_dict.py
racegym2d/env_visual_rays_dict.py
racegym2d/exp_observation.py
racegym2d/exp_observer.py
racegym2d/explained_env.py
racegym2d/finish_checker.py
racegym2d/trackenv_goal.py
racegym2d/vec_env_wrapper.py
racegym2d/vehicle_observer.py
racegym2d.egg-info/PKG-INFO
racegym2d.egg-info/SOURCES.txt
racegym2d.egg-info/dependency_links.txt
racegym2d.egg-info/requires.txt
racegym2d.egg-info/top_level.txt
racegym2d/rewards/__init__.py
racegym2d/rewards/abstract_reward_function.py
racegym2d/rewards/checkpoint_rewards.py
racegym2d/rewards/sdist_reward.py