Metadata-Version: 2.1
Name: racegym2d
Version: 0.1.1
Summary: Gym environments for 2D vehicle racing
Author: Christoph Hoeppke
